MANIFEST.in
Makefile
README
setup.py
test/__init__.py
test/__init__.pyc
test/test_compile.py
test/test_dist.py
test/__pycache__/test_compile.cpython-27-PYTEST.pyc
test/__pycache__/test_dist.cpython-27-PYTEST.pyc
tiddlywebplugins/__init__.py
tiddlywebplugins/diststore.py
tiddlywebplugins.diststore.egg-info/PKG-INFO
tiddlywebplugins.diststore.egg-info/SOURCES.txt
tiddlywebplugins.diststore.egg-info/dependency_links.txt
tiddlywebplugins.diststore.egg-info/namespace_packages.txt
tiddlywebplugins.diststore.egg-info/not-zip-safe
tiddlywebplugins.diststore.egg-info/requires.txt
tiddlywebplugins.diststore.egg-info/top_level.txt