Metadata-Version: 1.0
Name: tiddlywebplugins.diststore
Version: 0.7
Summary: Use multiple stores in the same TiddlyWeb instance.
Home-page: http://pypi.python.org/pypi/tiddlywebplugins.diststore
Author: Chris Dent
Author-email: cdent@peermore.com
License: UNKNOWN
Platform: Posix; MacOS X; Windows
